constcheck/__init__.py
constcheck/__main__.py
constcheck/_config.py
constcheck/_core.py
constcheck/_main.py
constcheck/_objects.py
constcheck/_typing.py
constcheck/_utils.py
constcheck/_version.py
constcheck/py.typed
constcheck-0.13.0.dist-info/METADATA
constcheck-0.13.0.dist-info/WHEEL
constcheck-0.13.0.dist-info/entry_points.txt
constcheck-0.13.0.dist-info/licenses/LICENSE
constcheck-0.13.0.dist-info/RECORD
