Metadata-Version: 2.4
Name: constcheck
Version: 0.13.0
Summary: Check Python files for repeat use of strings
License: MIT
License-File: LICENSE
Keywords: check,const,constant,dry,str
Author: jshwi
Author-email: stephen@jshwisolutions.com
Maintainer: jshwi
Maintainer-email: stephen@jshwisolutions.com
Requires-Python: >=3.10,<4.0
Classifier: License :: OSI Approved :: MIT License
Classifier: Programming Language :: Python :: 3
Classifier: Programming Language :: Python :: 3.10
Classifier: Programming Language :: Python :: 3.11
Classifier: Programming Language :: Python :: 3.12
Classifier: Programming Language :: Python :: 3.13
Classifier: Programming Language :: Python :: 3.14
Requires-Dist: arcon (>=0,<1)
Requires-Dist: object-colors (>=2.0.1,<3.0.0)
Requires-Dist: typing-extensions (>=4.9.0,<5.0.0)
Project-URL: Documentation, https://constcheck.readthedocs.io/en/latest
Project-URL: Homepage, https://pypi.org/project/constcheck/
Project-URL: Repository, https://github.com/jshwi/constcheck
